keywordanalyz/__init__.py
keywordanalyz/keywordanalyz.py
keywordanalyz-0.2.0.dist-info/LICENSE
keywordanalyz-0.2.0.dist-info/METADATA
keywordanalyz-0.2.0.dist-info/WHEEL
keywordanalyz-0.2.0.dist-info/RECORD
