Metadata-Version: 2.3
Name: keywordanalyz
Version: 0.2.0
Summary: A keyword analyser which uses YAKE and Lingua
License: Unlicense
Author: Pinguin
Author-email: ponguout@posteo.net
Requires-Python: >=3.13
Classifier: License :: OSI Approved
Classifier: Programming Language :: Python :: 3
Classifier: Programming Language :: Python :: 3.13
Requires-Dist: lingua-language-detector (>=2.1.1,<3.0.0)
Requires-Dist: yake (>=0.6.0,<0.7.0)
Project-URL: Bug Tracker, https://codeberg.org/pinguin/keywordanalyz/issues
Project-URL: Repository, https://codeberg.org/pinguin/keywordanalyz
